poethu/__init__.py
poethu/poethu.py
poethu-1.0.4.dist-info/METADATA
poethu-1.0.4.dist-info/WHEEL
poethu-1.0.4.dist-info/top_level.txt
poethu-1.0.4.dist-info/RECORD
