Metadata-Version: 2.1
Name: poethu
Version: 1.0.4
Summary: An unofficial Python wrapper for the poet.hu API
Home-page: https://github.com/bxn4/poethu
Author: BXn4 (Bence)
License: MIT
Keywords: python poet API
Classifier: Development Status :: 5 - Production/Stable
Classifier: License :: OSI Approved :: MIT License
Classifier: Programming Language :: Python :: 3
Classifier: Operating System :: Unix
Classifier: Operating System :: MacOS :: MacOS X
Classifier: Operating System :: Microsoft :: Windows
Requires-Python: >=3.0
Requires-Dist: requests
